README.md
setup.cfg
setup.py
distributions_name/Binomialdistribution.py
distributions_name/Gaussiandistribution.py
distributions_name/Generaldistribution.py
distributions_name/__init__.py
distributions_name.egg-info/PKG-INFO
distributions_name.egg-info/SOURCES.txt
distributions_name.egg-info/dependency_links.txt
distributions_name.egg-info/not-zip-safe
distributions_name.egg-info/top_level.txt